DataProfiler-0.13.4.data/data/resources/__init__.py
DataProfiler-0.13.4.data/data/resources/labelers/column_name_labeler/data_labeler_parameters.json
DataProfiler-0.13.4.data/data/resources/labelers/column_name_labeler/label_mapping.json
DataProfiler-0.13.4.data/data/resources/labelers/column_name_labeler/model_parameters.json
DataProfiler-0.13.4.data/data/resources/labelers/column_name_labeler/postprocessor_parameters.json
DataProfiler-0.13.4.data/data/resources/labelers/column_name_labeler/preprocessor_parameters.json
DataProfiler-0.13.4.data/data/resources/labelers/regex_model/data_labeler_parameters.json
DataProfiler-0.13.4.data/data/resources/labelers/regex_model/label_mapping.json
DataProfiler-0.13.4.data/data/resources/labelers/regex_model/model_parameters.json
DataProfiler-0.13.4.data/data/resources/labelers/regex_model/postprocessor_parameters.json
DataProfiler-0.13.4.data/data/resources/labelers/regex_model/preprocessor_parameters.json
DataProfiler-0.13.4.data/data/resources/labelers/structured_model/data_labeler_parameters.json
DataProfiler-0.13.4.data/data/resources/labelers/structured_model/label_mapping.json
DataProfiler-0.13.4.data/data/resources/labelers/structured_model/model.keras
DataProfiler-0.13.4.data/data/resources/labelers/structured_model/model_parameters.json
DataProfiler-0.13.4.data/data/resources/labelers/structured_model/postprocessor_parameters.json
DataProfiler-0.13.4.data/data/resources/labelers/structured_model/preprocessor_parameters.json
DataProfiler-0.13.4.data/data/resources/labelers/unstructured_model/data_labeler_parameters.json
DataProfiler-0.13.4.data/data/resources/labelers/unstructured_model/label_mapping.json
DataProfiler-0.13.4.data/data/resources/labelers/unstructured_model/model.keras
DataProfiler-0.13.4.data/data/resources/labelers/unstructured_model/model_parameters.json
DataProfiler-0.13.4.data/data/resources/labelers/unstructured_model/postprocessor_parameters.json
DataProfiler-0.13.4.dist-info/LICENSE
DataProfiler-0.13.4.dist-info/METADATA
DataProfiler-0.13.4.dist-info/WHEEL
DataProfiler-0.13.4.dist-info/top_level.txt
DataProfiler-0.13.4.dist-info/RECORD
