Metadata-Version: 2.1
Name: DataProfiler
Version: 0.13.4
Summary: What is in your data? Detect schema, statistics and entities in almost any file.
Home-page: https://github.com/capitalone/data-profiler
Author: Jeremy Goodsitt, Taylor Turner, Michael Davis, Kenny Bean, Tyler Farnan
License: Apache License, Version 2.0
Keywords: Data Investigation
Classifier: Development Status :: 5 - Production/Stable
Classifier: Intended Audience :: Developers
Classifier: Intended Audience :: Education
Classifier: Intended Audience :: Information Technology
Classifier: Intended Audience :: Science/Research
Classifier: Intended Audience :: System Administrators
Classifier: Topic :: Education
Classifier: Topic :: Scientific/Engineering
Classifier: Topic :: Scientific/Engineering :: Information Analysis
Classifier: Topic :: Security
Classifier: Topic :: Software Development :: Build Tools
Classifier: License :: OSI Approved :: Apache Software License
Classifier: Programming Language :: Python :: 3
Requires-Python: >=3.9
License-File: LICENSE
Requires-Dist: h5py>=2.10.0
Requires-Dist: wheel>=0.33.1
Requires-Dist: numpy<2.0.0
Requires-Dist: pandas>=1.1.2
Requires-Dist: python-dateutil>=2.7.5
Requires-Dist: pytz>=2020.1
Requires-Dist: pyarrow>=1.0.1
Requires-Dist: chardet>=3.0.4
Requires-Dist: fastavro>=1.1.0
Requires-Dist: python-snappy>=0.7.1
Requires-Dist: charset-normalizer>=1.3.6
Requires-Dist: psutil>=4.0.0
Requires-Dist: scipy>=1.10.0
Requires-Dist: requests==2.32.*
Requires-Dist: networkx>=2.5.1
Requires-Dist: typing-extensions>=3.10.0.2
Requires-Dist: HLL>=2.0.3
Requires-Dist: datasketches>=4.1.0
Requires-Dist: packaging>=23.0
Requires-Dist: boto3>=1.28.61
Requires-Dist: versioneer
Provides-Extra: full
Requires-Dist: scikit-learn>=0.23.2; extra == "full"
Requires-Dist: keras<=3.4.0; extra == "full"
Requires-Dist: rapidfuzz>=2.6.1; extra == "full"
Requires-Dist: tqdm>=4.0.0; extra == "full"
Requires-Dist: matplotlib<3.9.0,>=3.3.3; extra == "full"
Requires-Dist: seaborn>=0.11.1; extra == "full"
Requires-Dist: tensorflow>=2.16.0; sys_platform != "darwin" and extra == "full"
Requires-Dist: tensorflow>=2.16.0; (sys_platform == "darwin" and platform_machine != "arm64") and extra == "full"
Requires-Dist: tensorflow-macos>=2.16.0; (sys_platform == "darwin" and platform_machine == "arm64") and extra == "full"
Provides-Extra: ml
Requires-Dist: scikit-learn>=0.23.2; extra == "ml"
Requires-Dist: keras<=3.4.0; extra == "ml"
Requires-Dist: rapidfuzz>=2.6.1; extra == "ml"
Requires-Dist: tqdm>=4.0.0; extra == "ml"
Requires-Dist: tensorflow>=2.16.0; sys_platform != "darwin" and extra == "ml"
Requires-Dist: tensorflow>=2.16.0; (sys_platform == "darwin" and platform_machine != "arm64") and extra == "ml"
Requires-Dist: tensorflow-macos>=2.16.0; (sys_platform == "darwin" and platform_machine == "arm64") and extra == "ml"
Provides-Extra: reports
Requires-Dist: matplotlib<3.9.0,>=3.3.3; extra == "reports"
Requires-Dist: seaborn>=0.11.1; extra == "reports"
